{"className":"paladin","spec":"retribution","players":[{"name":"Qrva","realm":{"key":{"href":"https://eu.api.blizzard.com/data/wow/realm/580?namespace=dynamic-eu"},"name":"Blackmoore","id":580,"slug":"blackmoore"},"mainStats":[{"title":"stamina","value":2790},{"title":"strength","value":1650},{"title":"intellect","value":449},{"title":"agility","value":155}],"offStats":[{"title":"mastery","value":790},{"title":"haste","value":637},{"title":"crit","value":512},{"title":"versatility","value":278}],"defStats":[{"title":"avoidance","value":69},{"title":"dodge","value":0},{"title":"parry","value":0},{"title":"block","value":0}],"talents":[343527,326732,115750,114154,152262,326734,343721],"items":[{"id":178824,"slot":"FINGER_1","ilvl":252,"enchantments":[6166],"sockets":[173128],"bonuses":[7622,7359,6652,1566,6646,7576],"spells":[]},{"id":186377,"slot":"FINGER_2","ilvl":259,"enchantments":[6166],"sockets":[173128],"bonuses":[7187,6652,1498,6646,7576],"spells":[]},{"id":186438,"slot":"TRINKET_1","ilvl":259,"enchantments":[],"sockets":[],"bonuses":[7187,6652,1498,6646],"spells":[355297,355298]},{"id":186423,"slot":"TRINKET_2","ilvl":252,"enchantments":[],"sockets":[],"bonuses":[7187,6652,1498,6646],"spells":[355313]},{"id":186403,"slot":"MAIN_HAND","ilvl":252,"enchantments":[6228,6200],"sockets":[],"bonuses":[7187,6652,1498,6646],"spells":[]}],"legendaries":[{"id":171418,"slot":"LEGENDARY","ilvl":262,"enchantments":[6192],"sockets":[173128],"bonuses":[7067,7451,6648,6650,1559,6935],"spells":[337257]}],"covenant":{"covenant":"Kyrian","renownLevel":80,"soulbind":"Forgelite Prime Mikanikos","traits":[{"tier":0,"id":333950,"type":"spell"},{"tier":1,"id":182778,"type":"item","socketType":"POTENCY"},{"tier":2,"id":331609,"type":"spell"},{"tier":3,"id":182448,"type":"item","socketType":"FINESSE"},{"tier":4,"id":331726,"type":"spell"},{"tier":5,"id":187506,"type":"item","socketType":"ENDURANCE"},{"tier":6,"id":182336,"type":"item","socketType":"ENDURANCE"},{"tier":7,"id":333935,"type":"spell"},{"tier":8,"id":182608,"type":"item","socketType":"POTENCY"},{"tier":9,"id":352186,"type":"spell"},{"tier":10,"id":182304,"type":"item","socketType":"ENDURANCE"},{"tier":11,"id":352188,"type":"spell"}]}},{"name":"Стрей","realm":{"key":{"href":"https://eu.api.blizzard.com/data/wow/realm/1928?namespace=dynamic-eu"},"name":"Goldrinn","id":1928,"slug":"goldrinn"},"mainStats":[{"title":"stamina","value":2698},{"title":"strength","value":1596},{"title":"intellect","value":450},{"title":"agility","value":157}],"offStats":[{"title":"haste","value":720},{"title":"mastery","value":638},{"title":"crit","value":496},{"title":"versatility","value":340}],"defStats":[{"title":"avoidance","value":50},{"title":"dodge","value":0},{"title":"parry","value":0},{"title":"block","value":0}],"talents":[343527,326732,234299,114154,152262,326734,343721],"items":[{"id":186290,"slot":"FINGER_1","ilvl":252,"enchantments":[6164],"sockets":[173127],"bonuses":[7187,6652,7576,1498,6646],"spells":[]},{"id":178824,"slot":"FINGER_2","ilvl":252,"enchantments":[6168],"sockets":[],"bonuses":[7622,7359,6652,7575,1566,6646],"spells":[]},{"id":186423,"slot":"TRINKET_1","ilvl":252,"enchantments":[],"sockets":[],"bonuses":[7187,41,1498,6646],"spells":[355313]},{"id":186438,"slot":"TRINKET_2","ilvl":246,"enchantments":[],"sockets":[],"bonuses":[7188,40,1485,6646],"spells":[355297,355298]},{"id":178713,"slot":"MAIN_HAND","ilvl":252,"enchantments":[6229],"sockets":[],"bonuses":[7650,7359,6652,1566,6646],"spells":[]}],"legendaries":[{"id":171418,"slot":"LEGENDARY","ilvl":262,"enchantments":[6192],"sockets":[173127],"bonuses":[7679,6647,6650,6935,7451,1559],"spells":[355098]}],"covenant":{"covenant":"Kyrian","renownLevel":80,"soulbind":"Pelagos","traits":[{"tier":0,"id":328266,"type":"spell"},{"tier":1,"id":182778,"type":"item","socketType":"POTENCY"},{"tier":2,"id":328261,"type":"spell"},{"tier":3,"id":182307,"type":"item","socketType":"ENDURANCE"},{"tier":4,"id":328263,"type":"spell"},{"tier":5,"id":182608,"type":"item","socketType":"POTENCY"},{"tier":6,"id":182448,"type":"item","socketType":"FINESSE"},{"tier":7,"id":328257,"type":"spell"},{"tier":8,"id":182462,"type":"item","socketType":"POTENCY"},{"tier":9,"id":351146,"type":"spell"},{"tier":10,"id":187506,"type":"item","socketType":"ENDURANCE"},{"tier":11,"id":351149,"type":"spell"}]}},{"name":"Jirí","realm":{"key":{"href":"https://eu.api.blizzard.com/data/wow/realm/559?namespace=dynamic-eu"},"name":"Stormreaver","id":559,"slug":"stormreaver"},"mainStats":[{"title":"stamina","value":2779},{"title":"strength","value":1638},{"title":"intellect","value":452},{"title":"agility","value":158}],"offStats":[{"title":"mastery","value":663},{"title":"haste","value":567},{"title":"versatility","value":462},{"title":"crit","value":329}],"defStats":[{"title":"dodge","value":0},{"title":"parry","value":0},{"title":"block","value":0},{"title":"avoidance","value":0}],"talents":[343527,326732,115750,114154,152262,326734,343721],"items":[{"id":186290,"slot":"FINGER_1","ilvl":252,"enchantments":[6170],"sockets":[173130],"bonuses":[7187,6652,1498,6646,7576],"spells":[]},{"id":186376,"slot":"FINGER_2","ilvl":252,"enchantments":[6170],"sockets":[173130],"bonuses":[7187,6652,1498,6646,7576],"spells":[]},{"id":186438,"slot":"TRINKET_1","ilvl":259,"enchantments":[],"sockets":[],"bonuses":[7187,42,1498,6646],"spells":[355297,355298]},{"id":179342,"slot":"TRINKET_2","ilvl":252,"enchantments":[],"sockets":[],"bonuses":[7608,7359,6652,1566,6646],"spells":[329831]},{"id":186410,"slot":"MAIN_HAND","ilvl":259,"enchantments":[6229],"sockets":[],"bonuses":[7187,6652,1498,6646,7748],"spells":[358571]}],"legendaries":[{"id":171418,"slot":"LEGENDARY","ilvl":262,"enchantments":[6192],"sockets":[173130],"bonuses":[7679,6649,6648,6935,7451,1559],"spells":[355098]}],"covenant":{"covenant":"Kyrian","renownLevel":80,"soulbind":"Pelagos","traits":[{"tier":0,"id":328266,"type":"spell"},{"tier":1,"id":182778,"type":"item","socketType":"POTENCY"},{"tier":2,"id":328261,"type":"spell"},{"tier":3,"id":187506,"type":"item","socketType":"ENDURANCE"},{"tier":4,"id":328265,"type":"spell"},{"tier":5,"id":182608,"type":"item","socketType":"POTENCY"},{"tier":6,"id":182448,"type":"item","socketType":"FINESSE"},{"tier":7,"id":328257,"type":"spell"},{"tier":8,"id":182559,"type":"item","socketType":"POTENCY"},{"tier":9,"id":351146,"type":"spell"},{"tier":10,"id":182307,"type":"item","socketType":"ENDURANCE"},{"tier":11,"id":351149,"type":"spell"}]}},{"name":"Derrý","realm":{"key":{"href":"https://eu.api.blizzard.com/data/wow/realm/544?namespace=dynamic-eu"},"name":"Ner'zhul","id":544,"slug":"nerzhul"},"mainStats":[{"title":"stamina","value":2658},{"title":"strength","value":1566},{"title":"intellect","value":452},{"title":"agility","value":158}],"offStats":[{"title":"crit","value":709},{"title":"mastery","value":613},{"title":"haste","value":582},{"title":"versatility","value":197}],"defStats":[{"title":"dodge","value":0},{"title":"parry","value":0},{"title":"block","value":0},{"title":"avoidance","value":0}],"talents":[269569,326732,234299,230332,152262,326734,343721],"items":[{"id":179355,"slot":"FINGER_1","ilvl":249,"enchantments":[6164],"sockets":[],"bonuses":[7621,7359,6652,7575,1563,6646],"spells":[]},{"id":178871,"slot":"FINGER_2","ilvl":249,"enchantments":[6164],"sockets":[],"bonuses":[7621,7359,6652,7575,1563,6646],"spells":[]},{"id":179342,"slot":"TRINKET_1","ilvl":246,"enchantments":[],"sockets":[],"bonuses":[7359,6652,7606,1560,6646],"spells":[329831]},{"id":178771,"slot":"TRINKET_2","ilvl":246,"enchantments":[],"sockets":[],"bonuses":[7359,6652,7606,1560,6646],"spells":[345465]},{"id":179330,"slot":"MAIN_HAND","ilvl":249,"enchantments":[6229,6200],"sockets":[],"bonuses":[7649,7359,6652,1563,6646],"spells":[]}],"legendaries":[{"id":171418,"slot":"LEGENDARY","ilvl":262,"enchantments":[],"sockets":[173130],"bonuses":[7067,7451,6649,6648,1559,6935],"spells":[337257]}],"covenant":{"covenant":"Kyrian","renownLevel":80,"soulbind":"Pelagos","traits":[{"tier":0,"id":328266,"type":"spell"},{"tier":1,"id":182778,"type":"item","socketType":"POTENCY"},{"tier":2,"id":328261,"type":"spell"},{"tier":3,"id":187506,"type":"item","socketType":"ENDURANCE"},{"tier":4,"id":328263,"type":"spell"},{"tier":5,"id":182608,"type":"item","socketType":"POTENCY"},{"tier":6,"id":182448,"type":"item","socketType":"FINESSE"},{"tier":7,"id":328257,"type":"spell"},{"tier":8,"id":182462,"type":"item","socketType":"POTENCY"},{"tier":9,"id":351146,"type":"spell"},{"tier":10,"id":182304,"type":"item","socketType":"ENDURANCE"},{"tier":11,"id":351149,"type":"spell"}]}},{"name":"Черноевымя","realm":{"key":{"href":"https://eu.api.blizzard.com/data/wow/realm/1604?namespace=dynamic-eu"},"name":"Soulflayer","id":1604,"slug":"soulflayer"},"mainStats":[{"title":"stamina","value":2662},{"title":"strength","value":1551},{"title":"intellect","value":448},{"title":"agility","value":155}],"offStats":[{"title":"mastery","value":881},{"title":"haste","value":793},{"title":"crit","value":257},{"title":"versatility","value":162}],"defStats":[{"title":"dodge","value":0},{"title":"parry","value":0},{"title":"block","value":0},{"title":"avoidance","value":0}],"talents":[269569,326732,234299,230332,152262,326734,343721],"items":[{"id":179355,"slot":"FINGER_1","ilvl":252,"enchantments":[6164],"sockets":[],"bonuses":[7622,7359,6652,7574,1566,6646],"spells":[]},{"id":178824,"slot":"FINGER_2","ilvl":252,"enchantments":[6164],"sockets":[],"bonuses":[7622,7359,6652,7575,1566,6646],"spells":[]},{"id":178771,"slot":"TRINKET_1","ilvl":246,"enchantments":[],"sockets":[],"bonuses":[7359,6652,7606,1560,6646],"spells":[345465]},{"id":179342,"slot":"TRINKET_2","ilvl":252,"enchantments":[],"sockets":[],"bonuses":[7608,7359,41,1566,6646],"spells":[329831]},{"id":179330,"slot":"MAIN_HAND","ilvl":246,"enchantments":[6228,6200],"sockets":[],"bonuses":[7359,6652,7648,1560,6646],"spells":[]}],"legendaries":[{"id":171418,"slot":"LEGENDARY","ilvl":262,"enchantments":[],"sockets":[173127],"bonuses":[7067,6648,6649,6935,7451,1559],"spells":[337257]}],"covenant":{"covenant":"Kyrian","renownLevel":80,"soulbind":"Pelagos","traits":[{"tier":0,"id":328266,"type":"spell"},{"tier":1,"id":182608,"type":"item","socketType":"POTENCY"},{"tier":2,"id":328261,"type":"spell"},{"tier":3,"id":187506,"type":"item","socketType":"ENDURANCE"},{"tier":4,"id":328263,"type":"spell"},{"tier":5,"id":182778,"type":"item","socketType":"POTENCY"},{"tier":6,"id":182448,"type":"item","socketType":"FINESSE"},{"tier":7,"id":328257,"type":"spell"},{"tier":8,"id":182559,"type":"item","socketType":"POTENCY"},{"tier":9,"id":351146,"type":"spell"},{"tier":10,"id":182304,"type":"item","socketType":"ENDURANCE"},{"tier":11,"id":351149,"type":"spell"}]}},{"name":"Mixtraz","realm":{"key":{"href":"https://eu.api.blizzard.com/data/wow/realm/506?namespace=dynamic-eu"},"name":"Draenor","id":506,"slug":"draenor"},"mainStats":[{"title":"stamina","value":2655},{"title":"strength","value":1590},{"title":"intellect","value":452},{"title":"agility","value":158}],"offStats":[{"title":"haste","value":788},{"title":"mastery","value":688},{"title":"crit","value":435},{"title":"versatility","value":213}],"defStats":[{"title":"dodge","value":0},{"title":"parry","value":0},{"title":"block","value":0},{"title":"avoidance","value":0}],"talents":[343527,326732,234299,114154,152262,85804,343721],"items":[{"id":178824,"slot":"FINGER_1","ilvl":246,"enchantments":[6168],"sockets":[],"bonuses":[7359,6652,7574,7620,1560,6646],"spells":[]},{"id":178933,"slot":"FINGER_2","ilvl":246,"enchantments":[6168],"sockets":[173130],"bonuses":[7359,6652,7576,7620,1560,6646],"spells":[]},{"id":178771,"slot":"TRINKET_1","ilvl":246,"enchantments":[],"sockets":[],"bonuses":[7359,6652,7606,1560,6646],"spells":[345465]},{"id":179342,"slot":"TRINKET_2","ilvl":252,"enchantments":[],"sockets":[],"bonuses":[7608,7359,6652,1566,6646],"spells":[329831]},{"id":178780,"slot":"MAIN_HAND","ilvl":252,"enchantments":[6228,6200],"sockets":[],"bonuses":[7650,7359,6652,1566,6646],"spells":[]}],"legendaries":[{"id":171418,"slot":"LEGENDARY","ilvl":262,"enchantments":[6192],"sockets":[173130],"bonuses":[7679,7451,6649,6648,1559,6935],"spells":[355098]}],"covenant":{"covenant":"Kyrian","renownLevel":80,"soulbind":"Pelagos","traits":[{"tier":0,"id":328266,"type":"spell"},{"tier":1,"id":182559,"type":"item","socketType":"POTENCY"},{"tier":2,"id":328261,"type":"spell"},{"tier":3,"id":187506,"type":"item","socketType":"ENDURANCE"},{"tier":4,"id":328265,"type":"spell"},{"tier":5,"id":182778,"type":"item","socketType":"POTENCY"},{"tier":6,"id":182448,"type":"item","socketType":"FINESSE"},{"tier":7,"id":328257,"type":"spell"},{"tier":8,"id":182608,"type":"item","socketType":"POTENCY"},{"tier":9,"id":351146,"type":"spell"},{"tier":10,"id":182307,"type":"item","socketType":"ENDURANCE"},{"tier":11,"id":351149,"type":"spell"}]}},{"name":"Валандор","realm":{"key":{"href":"https://eu.api.blizzard.com/data/wow/realm/1602?namespace=dynamic-eu"},"name":"Gordunni","id":1602,"slug":"gordunni"},"mainStats":[{"title":"stamina","value":2709},{"title":"strength","value":1516},{"title":"intellect","value":450},{"title":"agility","value":157}],"offStats":[{"title":"mastery","value":826},{"title":"haste","value":780},{"title":"crit","value":389},{"title":"versatility","value":345}],"defStats":[{"title":"dodge","value":0},{"title":"parry","value":0},{"title":"block","value":0},{"title":"avoidance","value":0}],"talents":[343527,326732,234299,114154,152262,326734,343721],"items":[{"id":179355,"slot":"FINGER_1","ilvl":252,"enchantments":[6168],"sockets":[173130],"bonuses":[7622,7359,6652,1566,6646,7576],"spells":[]},{"id":178824,"slot":"FINGER_2","ilvl":246,"enchantments":[6168],"sockets":[173130],"bonuses":[7359,42,7620,1560,6646,7576],"spells":[]},{"id":185197,"slot":"TRINKET_1","ilvl":239,"enchantments":[],"sockets":[],"bonuses":[7314,1511,6646],"spells":[345228]},{"id":186423,"slot":"TRINKET_2","ilvl":252,"enchantments":[],"sockets":[],"bonuses":[7187,6652,1498,6646],"spells":[355313]},{"id":178713,"slot":"MAIN_HAND","ilvl":252,"enchantments":[6228],"sockets":[],"bonuses":[7650,7359,6652,1566,6646],"spells":[]}],"legendaries":[{"id":171418,"slot":"LEGENDARY","ilvl":262,"enchantments":[],"sockets":[173130],"bonuses":[7679,7451,6648,6649,1559,6935],"spells":[355098]}],"covenant":{"covenant":"Kyrian","renownLevel":80,"soulbind":"Pelagos","traits":[{"tier":0,"id":328266,"type":"spell"},{"tier":1,"id":182778,"type":"item","socketType":"POTENCY"},{"tier":2,"id":328261,"type":"spell"},{"tier":3,"id":182307,"type":"item","socketType":"ENDURANCE"},{"tier":4,"id":328265,"type":"spell"},{"tier":5,"id":182608,"type":"item","socketType":"POTENCY"},{"tier":6,"id":182448,"type":"item","socketType":"FINESSE"},{"tier":7,"id":328257,"type":"spell"},{"tier":8,"id":182559,"type":"item","socketType":"POTENCY"},{"tier":9,"id":351146,"type":"spell"},{"tier":10,"id":187506,"type":"item","socketType":"ENDURANCE"},{"tier":11,"id":351149,"type":"spell"}]}},{"name":"Алорк","realm":{"key":{"href":"https://eu.api.blizzard.com/data/wow/realm/1614?namespace=dynamic-eu"},"name":"Galakrond","id":1614,"slug":"galakrond"},"mainStats":[{"title":"stamina","value":2482},{"title":"strength","value":1525},{"title":"intellect","value":452},{"title":"agility","value":158}],"offStats":[{"title":"haste","value":624},{"title":"crit","value":499},{"title":"mastery","value":464},{"title":"versatility","value":295}],"defStats":[{"title":"dodge","value":0},{"title":"parry","value":0},{"title":"block","value":0},{"title":"avoidance","value":0}],"talents":[269569,326732,234299,230332,223817,326734,343721],"items":[{"id":178871,"slot":"FINGER_1","ilvl":252,"enchantments":[6164],"sockets":[],"bonuses":[7622,7359,6652,7574,1566,6646],"spells":[]},{"id":178870,"slot":"FINGER_2","ilvl":242,"enchantments":[6166],"sockets":[],"bonuses":[7359,6652,7575,7619,1556,6646],"spells":[]},{"id":186427,"slot":"TRINKET_1","ilvl":239,"enchantments":[],"sockets":[],"bonuses":[7188,6652,1485,6646],"spells":[355319]},{"id":179342,"slot":"TRINKET_2","ilvl":246,"enchantments":[],"sockets":[],"bonuses":[7359,6652,7606,1560,6646],"spells":[329831]},{"id":186410,"slot":"MAIN_HAND","ilvl":246,"enchantments":[6229,6200],"sockets":[],"bonuses":[7188,6652,1485,6646,7748],"spells":[358571]}],"legendaries":[{"id":171418,"slot":"LEGENDARY","ilvl":262,"enchantments":[],"sockets":[173128],"bonuses":[7679,7451,6649,6648,1559,6935],"spells":[355098]}],"covenant":{"covenant":"Kyrian","renownLevel":80,"soulbind":"Pelagos","traits":[{"tier":0,"id":328266,"type":"spell"},{"tier":1,"id":182778,"type":"item","socketType":"POTENCY"},{"tier":2,"id":328261,"type":"spell"},{"tier":3,"id":187506,"type":"item","socketType":"ENDURANCE"},{"tier":4,"id":328265,"type":"spell"},{"tier":5,"id":187507,"type":"item","socketType":"POTENCY"},{"tier":6,"id":182448,"type":"item","socketType":"FINESSE"},{"tier":7,"id":328257,"type":"spell"},{"tier":8,"id":182608,"type":"item","socketType":"POTENCY"},{"tier":9,"id":351146,"type":"spell"},{"tier":10,"id":182307,"type":"item","socketType":"ENDURANCE"},{"tier":11,"id":351149,"type":"spell"}]}},{"name":"Wookson","realm":{"key":{"href":"https://eu.api.blizzard.com/data/wow/realm/625?namespace=dynamic-eu"},"name":"Twisting Nether","id":625,"slug":"twisting-nether"},"mainStats":[{"title":"stamina","value":2681},{"title":"strength","value":1477},{"title":"intellect","value":452},{"title":"agility","value":158}],"offStats":[{"title":"mastery","value":715},{"title":"crit","value":572},{"title":"haste","value":491},{"title":"versatility","value":432}],"defStats":[{"title":"avoidance","value":74},{"title":"dodge","value":0},{"title":"parry","value":0},{"title":"block","value":0}],"talents":[269569,231832,234299,205191,152262,326734,343721],"items":[{"id":178781,"slot":"FINGER_1","ilvl":252,"enchantments":[6168],"sockets":[],"bonuses":[7622,7359,6652,7574,1566,6646],"spells":[]},{"id":179355,"slot":"FINGER_2","ilvl":246,"enchantments":[6168],"sockets":[],"bonuses":[7359,6652,7574,7620,1560,6646],"spells":[]},{"id":185304,"slot":"TRINKET_1","ilvl":233,"enchantments":[],"sockets":[],"bonuses":[7307,1505,6646],"spells":[336126]},{"id":185197,"slot":"TRINKET_2","ilvl":233,"enchantments":[],"sockets":[],"bonuses":[7313,1505,6646],"spells":[345228]},{"id":178780,"slot":"MAIN_HAND","ilvl":252,"enchantments":[6229],"sockets":[],"bonuses":[7650,7359,6652,1566,6646],"spells":[]}],"legendaries":[{"id":171416,"slot":"LEGENDARY","ilvl":262,"enchantments":[],"sockets":[],"bonuses":[7067,7451,6647,6648,1559],"spells":[337257]}],"covenant":{"covenant":"Kyrian","renownLevel":80,"soulbind":"Pelagos","traits":[{"tier":0,"id":328266,"type":"spell"},{"tier":1,"id":182778,"type":"item","socketType":"POTENCY"},{"tier":2,"id":328261,"type":"spell"},{"tier":3,"id":182307,"type":"item","socketType":"ENDURANCE"},{"tier":4,"id":328265,"type":"spell"},{"tier":5,"id":182608,"type":"item","socketType":"POTENCY"},{"tier":6,"id":182448,"type":"item","socketType":"FINESSE"},{"tier":7,"id":328257,"type":"spell"},{"tier":8,"id":182559,"type":"item","socketType":"POTENCY"},{"tier":9,"id":351146,"type":"spell"},{"tier":10,"id":182304,"type":"item","socketType":"ENDURANCE"},{"tier":11,"id":351149,"type":"spell"}]}},{"name":"Бомзитар","realm":{"key":{"href":"https://eu.api.blizzard.com/data/wow/realm/1925?namespace=dynamic-eu"},"name":"Eversong","id":1925,"slug":"eversong"},"mainStats":[{"title":"stamina","value":2102},{"title":"strength","value":1267},{"title":"intellect","value":447},{"title":"agility","value":159}],"offStats":[{"title":"haste","value":809},{"title":"crit","value":430},{"title":"mastery","value":306},{"title":"versatility","value":284}],"defStats":[{"title":"avoidance","value":48},{"title":"dodge","value":0},{"title":"parry","value":0},{"title":"block","value":0}],"talents":[267610,231832,234299,230332,152262,326734,231895],"items":[{"id":185894,"slot":"FINGER_1","ilvl":220,"enchantments":[],"sockets":[],"bonuses":[7575,7695,1492,6646],"spells":[]},{"id":178871,"slot":"FINGER_2","ilvl":236,"enchantments":[],"sockets":[],"bonuses":[7617,7359,6652,7575,1550,6646],"spells":[]},{"id":179350,"slot":"TRINKET_1","ilvl":236,"enchantments":[],"sockets":[],"bonuses":[7603,7359,6652,1550,6646],"spells":[330323]},{"id":178809,"slot":"TRINKET_2","ilvl":236,"enchantments":[],"sockets":[],"bonuses":[7603,7359,6652,1550,6646],"spells":[345801]},{"id":178713,"slot":"MAIN_HAND","ilvl":236,"enchantments":[],"sockets":[],"bonuses":[7645,7359,6652,1550,6646],"spells":[]}],"legendaries":[{"id":171418,"slot":"LEGENDARY","ilvl":190,"enchantments":[],"sockets":[],"bonuses":[7679,6716,6649,6650,1487,6935],"spells":[355098]}],"covenant":{"covenant":"Kyrian","renownLevel":80,"soulbind":"Pelagos","traits":[{"tier":0,"id":328266,"type":"spell"},{"tier":1,"id":182667,"type":"item","socketType":"POTENCY"},{"tier":2,"id":328261,"type":"spell"},{"tier":3,"id":182753,"type":"item","socketType":"ENDURANCE"},{"tier":4,"id":328265,"type":"spell"},{"tier":5,"id":182622,"type":"item","socketType":"POTENCY"},{"tier":6,"id":182307,"type":"item","socketType":"ENDURANCE"},{"tier":7,"id":328257,"type":"spell"},{"tier":8,"id":182675,"type":"item","socketType":"POTENCY"},{"tier":9,"id":351147,"type":"spell"},{"tier":10,"id":182461,"type":"item","socketType":"FINESSE"},{"tier":11,"id":351149,"type":"spell"}]}},{"name":"Исели","realm":{"key":{"href":"https://eu.api.blizzard.com/data/wow/realm/1602?namespace=dynamic-eu"},"name":"Gordunni","id":1602,"slug":"gordunni"},"mainStats":[{"title":"stamina","value":2699},{"title":"strength","value":1509},{"title":"intellect","value":450},{"title":"agility","value":156}],"offStats":[{"title":"mastery","value":788},{"title":"haste","value":586},{"title":"crit","value":512},{"title":"versatility","value":375}],"defStats":[{"title":"dodge","value":0},{"title":"parry","value":0},{"title":"block","value":0},{"title":"avoidance","value":0}],"talents":[343527,326732,115750,114154,152262,326734,343721],"items":[{"id":186377,"slot":"FINGER_1","ilvl":246,"enchantments":[6168],"sockets":[],"bonuses":[7188,6652,7575,1485,6646],"spells":[]},{"id":178824,"slot":"FINGER_2","ilvl":252,"enchantments":[6168],"sockets":[173128],"bonuses":[7622,7359,6652,1566,6646,7576],"spells":[]},{"id":186438,"slot":"TRINKET_1","ilvl":246,"enchantments":[],"sockets":[],"bonuses":[7188,6652,1485,6646],"spells":[355297,355298]},{"id":185197,"slot":"TRINKET_2","ilvl":236,"enchantments":[],"sockets":[],"bonuses":[7863,1508,6646],"spells":[345228]},{"id":186403,"slot":"MAIN_HAND","ilvl":252,"enchantments":[6228,6200],"sockets":[],"bonuses":[7187,6652,1498,6646],"spells":[]}],"legendaries":[{"id":171418,"slot":"LEGENDARY","ilvl":262,"enchantments":[],"sockets":[173128],"bonuses":[7679,7451,6649,6648,1559,6935],"spells":[355098]}],"covenant":{"covenant":"Kyrian","renownLevel":80,"soulbind":"Pelagos","traits":[{"tier":0,"id":328266,"type":"spell"},{"tier":1,"id":182778,"type":"item","socketType":"POTENCY"},{"tier":2,"id":328261,"type":"spell"},{"tier":3,"id":182304,"type":"item","socketType":"ENDURANCE"},{"tier":4,"id":328263,"type":"spell"},{"tier":5,"id":182559,"type":"item","socketType":"POTENCY"},{"tier":6,"id":182448,"type":"item","socketType":"FINESSE"},{"tier":7,"id":328257,"type":"spell"},{"tier":8,"id":182608,"type":"item","socketType":"POTENCY"},{"tier":9,"id":351146,"type":"spell"},{"tier":10,"id":187506,"type":"item","socketType":"ENDURANCE"},{"tier":11,"id":351149,"type":"spell"}]}},{"name":"Grekc","realm":{"key":{"href":"https://eu.api.blizzard.com/data/wow/realm/625?namespace=dynamic-eu"},"name":"Twisting Nether","id":625,"slug":"twisting-nether"},"mainStats":[{"title":"stamina","value":2679},{"title":"strength","value":1496},{"title":"intellect","value":452},{"title":"agility","value":158}],"offStats":[{"title":"mastery","value":916},{"title":"haste","value":553},{"title":"versatility","value":500},{"title":"crit","value":308}],"defStats":[{"title":"dodge","value":0},{"title":"parry","value":0},{"title":"block","value":0},{"title":"avoidance","value":0}],"talents":[343527,231832,234299,230332,152262,326734,343721],"items":[{"id":186290,"slot":"FINGER_1","ilvl":252,"enchantments":[6166],"sockets":[173129],"bonuses":[7187,6652,1498,6646,7576],"spells":[]},{"id":178870,"slot":"FINGER_2","ilvl":252,"enchantments":[6170],"sockets":[173129],"bonuses":[7622,7359,6652,7576,1566,6646],"spells":[]},{"id":186438,"slot":"TRINKET_1","ilvl":246,"enchantments":[],"sockets":[],"bonuses":[7188,6652,1485,6646],"spells":[355297,355298]},{"id":185197,"slot":"TRINKET_2","ilvl":236,"enchantments":[],"sockets":[],"bonuses":[7863,1508,6646],"spells":[345228]},{"id":186403,"slot":"MAIN_HAND","ilvl":252,"enchantments":[6228],"sockets":[],"bonuses":[7187,6652,1498,6646],"spells":[]}],"legendaries":[{"id":171418,"slot":"LEGENDARY","ilvl":262,"enchantments":[],"sockets":[173129],"bonuses":[7679,6648,6649,6935,7451,1559],"spells":[355098]}],"covenant":{"covenant":"Kyrian","renownLevel":80,"soulbind":"Pelagos","traits":[{"tier":0,"id":328266,"type":"spell"},{"tier":1,"id":182778,"type":"item","socketType":"POTENCY"},{"tier":2,"id":328261,"type":"spell"},{"tier":3,"id":187506,"type":"item","socketType":"ENDURANCE"},{"tier":4,"id":328265,"type":"spell"},{"tier":5,"id":182559,"type":"item","socketType":"POTENCY"},{"tier":6,"id":182307,"type":"item","socketType":"ENDURANCE"},{"tier":7,"id":328257,"type":"spell"},{"tier":8,"id":182608,"type":"item","socketType":"POTENCY"},{"tier":9,"id":351146,"type":"spell"},{"tier":10,"id":182304,"type":"item","socketType":"ENDURANCE"},{"tier":11,"id":351149,"type":"spell"}]}},{"name":"Centurio","realm":{"key":{"href":"https://eu.api.blizzard.com/data/wow/realm/547?namespace=dynamic-eu"},"name":"Runetotem","id":547,"slug":"runetotem"},"mainStats":[{"title":"stamina","value":2635},{"title":"strength","value":1591},{"title":"intellect","value":450},{"title":"agility","value":157}],"offStats":[{"title":"crit","value":767},{"title":"haste","value":614},{"title":"mastery","value":454},{"title":"versatility","value":382}],"defStats":[{"title":"dodge","value":0},{"title":"parry","value":0},{"title":"block","value":0},{"title":"avoidance","value":0}],"talents":[343527,231832,115750,230332,152262,85804,343721],"items":[{"id":179355,"slot":"FINGER_1","ilvl":252,"enchantments":[6166],"sockets":[173130],"bonuses":[7622,7359,6652,1566,6646,7576],"spells":[]},{"id":178848,"slot":"FINGER_2","ilvl":252,"enchantments":[6166],"sockets":[168636],"bonuses":[7622,7359,6652,7576,1566,6646],"spells":[]},{"id":179342,"slot":"TRINKET_1","ilvl":252,"enchantments":[],"sockets":[],"bonuses":[7608,7359,6652,1566,6646],"spells":[329831]},{"id":186438,"slot":"TRINKET_2","ilvl":246,"enchantments":[],"sockets":[],"bonuses":[7188,6652,1485,6646],"spells":[355297,355298]},{"id":179330,"slot":"MAIN_HAND","ilvl":246,"enchantments":[6228,6200],"sockets":[],"bonuses":[7359,6652,7648,1560,6646],"spells":[]}],"legendaries":[{"id":171418,"slot":"LEGENDARY","ilvl":262,"enchantments":[],"sockets":[173130],"bonuses":[7679,6647,6649,6935,7451,1559],"spells":[355098]}],"covenant":{"covenant":"Kyrian","renownLevel":80,"soulbind":"Pelagos","traits":[{"tier":0,"id":328266,"type":"spell"},{"tier":1,"id":182778,"type":"item","socketType":"POTENCY"},{"tier":2,"id":328261,"type":"spell"},{"tier":3,"id":182307,"type":"item","socketType":"ENDURANCE"},{"tier":4,"id":328263,"type":"spell"},{"tier":5,"id":182608,"type":"item","socketType":"POTENCY"},{"tier":6,"id":182448,"type":"item","socketType":"FINESSE"},{"tier":7,"id":328257,"type":"spell"},{"tier":8,"id":182559,"type":"item","socketType":"POTENCY"},{"tier":9,"id":351146,"type":"spell"},{"tier":10,"id":187506,"type":"item","socketType":"ENDURANCE"},{"tier":11,"id":351149,"type":"spell"}]}},{"name":"Сеншуй","realm":{"key":{"href":"https://eu.api.blizzard.com/data/wow/realm/1615?namespace=dynamic-eu"},"name":"Howling Fjord","id":1615,"slug":"howling-fjord"},"mainStats":[{"title":"stamina","value":2602},{"title":"strength","value":1466},{"title":"intellect","value":452},{"title":"agility","value":158}],"offStats":[{"title":"haste","value":734},{"title":"mastery","value":725},{"title":"crit","value":518},{"title":"versatility","value":277}],"defStats":[{"title":"avoidance","value":52},{"title":"dodge","value":0},{"title":"parry","value":0},{"title":"block","value":0}],"talents":[269569,231832,115750,114154,152262,326734,343721],"items":[{"id":178871,"slot":"FINGER_1","ilvl":246,"enchantments":[6170],"sockets":[173129],"bonuses":[7359,6652,7620,1560,6646,7576],"spells":[]},{"id":179355,"slot":"FINGER_2","ilvl":252,"enchantments":[6170],"sockets":[173129],"bonuses":[7622,7359,6652,1566,6646,7576],"spells":[]},{"id":178771,"slot":"TRINKET_1","ilvl":246,"enchantments":[],"sockets":[],"bonuses":[7606,7359,6652,1560,6646],"spells":[345465]},{"id":185197,"slot":"TRINKET_2","ilvl":220,"enchantments":[],"sockets":[],"bonuses":[7311,1492,6646],"spells":[345228]},{"id":179330,"slot":"MAIN_HAND","ilvl":246,"enchantments":[6229],"sockets":[],"bonuses":[7359,6652,7648,1560,6646],"spells":[]}],"legendaries":[{"id":171418,"slot":"LEGENDARY","ilvl":262,"enchantments":[4223],"sockets":[173129],"bonuses":[7679,6649,6647,6935,7451,1559],"spells":[355098]}],"covenant":{"covenant":"Kyrian","renownLevel":80,"soulbind":"Pelagos","traits":[{"tier":0,"id":328266,"type":"spell"},{"tier":1,"id":182778,"type":"item","socketType":"POTENCY"},{"tier":2,"id":328261,"type":"spell"},{"tier":3,"id":187506,"type":"item","socketType":"ENDURANCE"},{"tier":4,"id":328265,"type":"spell"},{"tier":5,"id":182559,"type":"item","socketType":"POTENCY"},{"tier":6,"id":182456,"type":"item","socketType":"FINESSE"},{"tier":7,"id":328257,"type":"spell"},{"tier":8,"id":182608,"type":"item","socketType":"POTENCY"},{"tier":9,"id":351146,"type":"spell"},{"tier":10,"id":182307,"type":"item","socketType":"ENDURANCE"},{"tier":11,"id":351149,"type":"spell"}]}},{"name":"Geneundreitt","realm":{"key":{"href":"https://eu.api.blizzard.com/data/wow/realm/531?namespace=dynamic-eu"},"name":"Dethecus","id":531,"slug":"dethecus"},"mainStats":[{"title":"stamina","value":2626},{"title":"strength","value":1383},{"title":"intellect","value":450},{"title":"agility","value":157}],"offStats":[{"title":"versatility","value":1357},{"title":"haste","value":372},{"title":"mastery","value":335},{"title":"crit","value":290}],"defStats":[{"title":"dodge","value":0},{"title":"parry","value":0},{"title":"block","value":0},{"title":"avoidance","value":0}],"talents":[269569,231832,234299,230332,152262,326734,343721],"items":[{"id":178870,"slot":"FINGER_1","ilvl":252,"enchantments":[6166],"sockets":[],"bonuses":[7622,7359,6652,7575,1566,6646],"spells":[]},{"id":185273,"slot":"FINGER_2","ilvl":236,"enchantments":[6168],"sockets":[],"bonuses":[6652,7575,7860,1508,6646],"spells":[]},{"id":185197,"slot":"TRINKET_1","ilvl":236,"enchantments":[],"sockets":[],"bonuses":[7863,1508,6646],"spells":[345228]},{"id":185278,"slot":"TRINKET_2","ilvl":236,"enchantments":[],"sockets":[],"bonuses":[7863,1508,6646],"spells":[345229]},{"id":178780,"slot":"MAIN_HAND","ilvl":236,"enchantments":[6228],"sockets":[],"bonuses":[7359,6652,7645,1550,6646],"spells":[]}],"legendaries":[{"id":171412,"slot":"LEGENDARY","ilvl":262,"enchantments":[6230],"sockets":[],"bonuses":[7064,6650,6648,7451,1559],"spells":[337247]}],"covenant":{"covenant":"Kyrian","renownLevel":80,"soulbind":"Pelagos","traits":[{"tier":0,"id":328266,"type":"spell"},{"tier":1,"id":182778,"type":"item","socketType":"POTENCY"},{"tier":2,"id":328261,"type":"spell"},{"tier":3,"id":182307,"type":"item","socketType":"ENDURANCE"},{"tier":4,"id":328265,"type":"spell"},{"tier":5,"id":182559,"type":"item","socketType":"POTENCY"},{"tier":6,"id":182461,"type":"item","socketType":"FINESSE"},{"tier":7,"id":328257,"type":"spell"},{"tier":8,"id":182608,"type":"item","socketType":"POTENCY"},{"tier":9,"id":351146,"type":"spell"},{"tier":10,"id":187506,"type":"item","socketType":"ENDURANCE"},{"tier":11,"id":351149,"type":"spell"}]}},{"name":"Drayygopala","realm":{"key":{"href":"https://eu.api.blizzard.com/data/wow/realm/572?namespace=dynamic-eu"},"name":"Malfurion","id":572,"slug":"malfurion"},"mainStats":[{"title":"stamina","value":2124},{"title":"strength","value":1383},{"title":"intellect","value":473},{"title":"agility","value":177}],"offStats":[{"title":"haste","value":691},{"title":"crit","value":396},{"title":"mastery","value":332},{"title":"versatility","value":312}],"defStats":[{"title":"avoidance","value":41},{"title":"dodge","value":0},{"title":"parry","value":0},{"title":"block","value":0}],"talents":[267610,231832,234299,230332,223817,326734,231895],"items":[{"id":186376,"slot":"FINGER_1","ilvl":239,"enchantments":[6166],"sockets":[],"bonuses":[7188,40,7575,1485,6646],"spells":[]},{"id":178871,"slot":"FINGER_2","ilvl":236,"enchantments":[6166],"sockets":[],"bonuses":[7617,7359,6652,7575,1550,6646],"spells":[]},{"id":186432,"slot":"TRINKET_1","ilvl":239,"enchantments":[],"sockets":[],"bonuses":[7188,6652,1485,6646],"spells":[355333]},{"id":178771,"slot":"TRINKET_2","ilvl":236,"enchantments":[],"sockets":[],"bonuses":[7603,7359,6652,1550,6646],"spells":[345465]},{"id":186410,"slot":"MAIN_HAND","ilvl":246,"enchantments":[6228],"sockets":[],"bonuses":[7188,6652,1485,6646,7748],"spells":[358571]}],"legendaries":[{"id":171418,"slot":"LEGENDARY","ilvl":235,"enchantments":[],"sockets":[173128],"bonuses":[7054,6758,6649,6647,1532,6935],"spells":[337594]}],"covenant":{"covenant":"Venthyr","renownLevel":79,"soulbind":"Theotar the Mad Duke","traits":[{"tier":0,"id":336239,"type":"spell"},{"tier":1,"id":182448,"type":"item","socketType":"FINESSE"},{"tier":2,"id":336147,"type":"spell"},{"tier":3,"id":182462,"type":"item","socketType":"POTENCY"},{"tier":4,"id":336184,"type":"spell"},{"tier":5,"id":182336,"type":"item","socketType":"ENDURANCE"},{"tier":6,"id":182559,"type":"item","socketType":"POTENCY"},{"tier":7,"id":336245,"type":"spell"},{"tier":8,"id":182608,"type":"item","socketType":"POTENCY"},{"tier":9,"id":351747,"type":"spell"},{"tier":10,"id":182456,"type":"item","socketType":"FINESSE"},{"tier":11,"id":351750,"type":"spell"}]}},{"name":"Тцарёв","realm":{"key":{"href":"https://eu.api.blizzard.com/data/wow/realm/1602?namespace=dynamic-eu"},"name":"Gordunni","id":1602,"slug":"gordunni"},"mainStats":[{"title":"stamina","value":2621},{"title":"strength","value":1585},{"title":"intellect","value":450},{"title":"agility","value":157}],"offStats":[{"title":"mastery","value":903},{"title":"haste","value":575},{"title":"crit","value":284},{"title":"versatility","value":244}],"defStats":[{"title":"dodge","value":0},{"title":"parry","value":0},{"title":"block","value":0},{"title":"avoidance","value":0}],"talents":[343527,326732,234299,230332,152262,326734,343721],"items":[{"id":178824,"slot":"FINGER_1","ilvl":246,"enchantments":[6168],"sockets":[173130],"bonuses":[7359,6652,7620,1560,6646,7576],"spells":[]},{"id":179355,"slot":"FINGER_2","ilvl":246,"enchantments":[6168],"sockets":[173130],"bonuses":[7359,6652,7576,7620,1560,6646],"spells":[]},{"id":179350,"slot":"TRINKET_1","ilvl":252,"enchantments":[],"sockets":[],"bonuses":[7608,7359,6652,1566,6646],"spells":[330323]},{"id":178771,"slot":"TRINKET_2","ilvl":246,"enchantments":[],"sockets":[],"bonuses":[7359,6652,7606,1560,6646],"spells":[345465]},{"id":186410,"slot":"MAIN_HAND","ilvl":246,"enchantments":[6229,6200],"sockets":[],"bonuses":[7188,6652,1485,6646,7748],"spells":[358571]}],"legendaries":[{"id":171418,"slot":"LEGENDARY","ilvl":262,"enchantments":[],"sockets":[173130],"bonuses":[7067,7451,6648,6650,1559,6935],"spells":[337257]}],"covenant":{"covenant":"Kyrian","renownLevel":80,"soulbind":"Pelagos","traits":[{"tier":0,"id":328266,"type":"spell"},{"tier":1,"id":182778,"type":"item","socketType":"POTENCY"},{"tier":2,"id":328261,"type":"spell"},{"tier":3,"id":187506,"type":"item","socketType":"ENDURANCE"},{"tier":4,"id":328263,"type":"spell"},{"tier":5,"id":182608,"type":"item","socketType":"POTENCY"},{"tier":6,"id":182448,"type":"item","socketType":"FINESSE"},{"tier":7,"id":328257,"type":"spell"},{"tier":8,"id":182559,"type":"item","socketType":"POTENCY"},{"tier":9,"id":351146,"type":"spell"},{"tier":10,"id":182307,"type":"item","socketType":"ENDURANCE"},{"tier":11,"id":351149,"type":"spell"}]}},{"name":"Middland","realm":{"key":{"href":"https://eu.api.blizzard.com/data/wow/realm/1309?namespace=dynamic-eu"},"name":"Pozzo dell'Eternità","id":1309,"slug":"pozzo-delleternità"},"mainStats":[{"title":"stamina","value":2261},{"title":"strength","value":1471},{"title":"intellect","value":452},{"title":"agility","value":158}],"offStats":[{"title":"mastery","value":642},{"title":"crit","value":602},{"title":"haste","value":530},{"title":"versatility","value":163}],"defStats":[{"title":"avoidance","value":30},{"title":"dodge","value":0},{"title":"parry","value":0},{"title":"block","value":0}],"talents":[269569,326732,234299,114154,152262,326734,317866],"items":[{"id":178872,"slot":"FINGER_1","ilvl":236,"enchantments":[6164],"sockets":[],"bonuses":[7617,7359,6652,7574,1550,6646],"spells":[]},{"id":178871,"slot":"FINGER_2","ilvl":246,"enchantments":[6168],"sockets":[],"bonuses":[7620,7359,6652,7575,1560,6646],"spells":[]},{"id":179350,"slot":"TRINKET_1","ilvl":246,"enchantments":[],"sockets":[],"bonuses":[7359,6652,7606,1560,6646],"spells":[330323]},{"id":178861,"slot":"TRINKET_2","ilvl":252,"enchantments":[],"sockets":[],"bonuses":[7608,7359,6652,1566,6646],"spells":[342427]},{"id":178713,"slot":"MAIN_HAND","ilvl":233,"enchantments":[6229,6188],"sockets":[],"bonuses":[7359,6652,7644,1547,6646],"spells":[]}],"legendaries":[{"id":171418,"slot":"LEGENDARY","ilvl":262,"enchantments":[],"sockets":[173127],"bonuses":[7679,7451,6647,6648,1559,6935],"spells":[355098]}],"covenant":{"covenant":"Kyrian","renownLevel":80,"soulbind":"Pelagos","traits":[{"tier":0,"id":328266,"type":"spell"},{"tier":1,"id":182465,"type":"item","socketType":"POTENCY"},{"tier":2,"id":328261,"type":"spell"},{"tier":3,"id":187506,"type":"item","socketType":"ENDURANCE"},{"tier":4,"id":328265,"type":"spell"},{"tier":5,"id":182608,"type":"item","socketType":"POTENCY"},{"tier":6,"id":182448,"type":"item","socketType":"FINESSE"},{"tier":7,"id":328257,"type":"spell"},{"tier":8,"id":182559,"type":"item","socketType":"POTENCY"},{"tier":9,"id":351146,"type":"spell"},{"tier":10,"id":182753,"type":"item","socketType":"ENDURANCE"},{"tier":11,"id":351149,"type":"spell"}]}},{"name":"Anestesia","realm":{"key":{"href":"https://eu.api.blizzard.com/data/wow/realm/501?namespace=dynamic-eu"},"name":"Arathor","id":501,"slug":"arathor"},"mainStats":[{"title":"stamina","value":2600},{"title":"strength","value":1603},{"title":"intellect","value":473},{"title":"agility","value":177}],"offStats":[{"title":"mastery","value":723},{"title":"haste","value":705},{"title":"crit","value":437},{"title":"versatility","value":236}],"defStats":[{"title":"dodge","value":0},{"title":"parry","value":0},{"title":"block","value":0},{"title":"avoidance","value":0}],"talents":[269569,326732,115750,230332,152262,85804,343721],"items":[{"id":178871,"slot":"FINGER_1","ilvl":252,"enchantments":[6168],"sockets":[],"bonuses":[7622,7359,6652,7575,1566,6646],"spells":[]},{"id":178824,"slot":"FINGER_2","ilvl":252,"enchantments":[6166],"sockets":[],"bonuses":[7622,7359,6652,7574,1566,6646],"spells":[]},{"id":179342,"slot":"TRINKET_1","ilvl":252,"enchantments":[],"sockets":[],"bonuses":[7608,7359,6652,1566,6646],"spells":[329831]},{"id":178771,"slot":"TRINKET_2","ilvl":252,"enchantments":[],"sockets":[],"bonuses":[7608,7359,6652,1566,6646],"spells":[345465]},{"id":186403,"slot":"MAIN_HAND","ilvl":252,"enchantments":[6229],"sockets":[],"bonuses":[7187,6652,1498,6646],"spells":[]}],"legendaries":[{"id":171418,"slot":"LEGENDARY","ilvl":262,"enchantments":[],"sockets":[173127],"bonuses":[7679,7451,6649,6647,1559,6935],"spells":[355098]}],"covenant":{"covenant":"Kyrian","renownLevel":80,"soulbind":"Pelagos","traits":[{"tier":0,"id":328266,"type":"spell"},{"tier":1,"id":182778,"type":"item","socketType":"POTENCY"},{"tier":2,"id":328261,"type":"spell"},{"tier":3,"id":182307,"type":"item","socketType":"ENDURANCE"},{"tier":4,"id":328263,"type":"spell"},{"tier":5,"id":182559,"type":"item","socketType":"POTENCY"},{"tier":6,"id":182448,"type":"item","socketType":"FINESSE"},{"tier":7,"id":328257,"type":"spell"},{"tier":8,"id":182608,"type":"item","socketType":"POTENCY"},{"tier":9,"id":351146,"type":"spell"},{"tier":10,"id":187506,"type":"item","socketType":"ENDURANCE"},{"tier":11,"id":351149,"type":"spell"}]}},{"name":"Pîxèl","realm":{"key":{"href":"https://eu.api.blizzard.com/data/wow/realm/542?namespace=dynamic-eu"},"name":"Hyjal","id":542,"slug":"hyjal"},"mainStats":[{"title":"stamina","value":2690},{"title":"strength","value":1501},{"title":"intellect","value":452},{"title":"agility","value":158}],"offStats":[{"title":"mastery","value":854},{"title":"crit","value":616},{"title":"haste","value":486},{"title":"versatility","value":228}],"defStats":[{"title":"avoidance","value":173},{"title":"dodge","value":0},{"title":"parry","value":0},{"title":"block","value":0}],"talents":[343527,231832,234299,230332,152262,85804,343721],"items":[{"id":178872,"slot":"FINGER_1","ilvl":252,"enchantments":[6168],"sockets":[173130],"bonuses":[7622,7359,6652,1566,6646,7576],"spells":[]},{"id":178869,"slot":"FINGER_2","ilvl":252,"enchantments":[6168],"sockets":[173130],"bonuses":[7622,7359,6652,1566,6646,7576],"spells":[]},{"id":178771,"slot":"TRINKET_1","ilvl":246,"enchantments":[],"sockets":[],"bonuses":[7359,6652,7606,1560,6646],"spells":[345465]},{"id":185197,"slot":"TRINKET_2","ilvl":233,"enchantments":[],"sockets":[],"bonuses":[7313,1505,6646],"spells":[345228]},{"id":186410,"slot":"MAIN_HAND","ilvl":246,"enchantments":[6229],"sockets":[],"bonuses":[7188,6652,1485,6646,7745,7746,7747],"spells":[357585,358569]}],"legendaries":[{"id":171418,"slot":"LEGENDARY","ilvl":262,"enchantments":[],"sockets":[173127],"bonuses":[7679,7451,6649,6648,1559,6935],"spells":[355098]}],"covenant":{"covenant":"Kyrian","renownLevel":80,"soulbind":"Pelagos","traits":[{"tier":0,"id":328266,"type":"spell"},{"tier":1,"id":182778,"type":"item","socketType":"POTENCY"},{"tier":2,"id":328261,"type":"spell"},{"tier":3,"id":182336,"type":"item","socketType":"ENDURANCE"},{"tier":4,"id":328263,"type":"spell"},{"tier":5,"id":182608,"type":"item","socketType":"POTENCY"},{"tier":6,"id":182448,"type":"item","socketType":"FINESSE"},{"tier":7,"id":328257,"type":"spell"},{"tier":8,"id":182559,"type":"item","socketType":"POTENCY"},{"tier":9,"id":351146,"type":"spell"},{"tier":10,"id":187506,"type":"item","socketType":"ENDURANCE"},{"tier":11,"id":351149,"type":"spell"}]}},{"name":"Punyelf","realm":{"key":{"href":"https://eu.api.blizzard.com/data/wow/realm/506?namespace=dynamic-eu"},"name":"Draenor","id":506,"slug":"draenor"},"mainStats":[{"title":"stamina","value":2648},{"title":"strength","value":1593},{"title":"intellect","value":452},{"title":"agility","value":158}],"offStats":[{"title":"haste","value":876},{"title":"crit","value":659},{"title":"mastery","value":527},{"title":"versatility","value":229}],"defStats":[{"title":"dodge","value":0},{"title":"parry","value":0},{"title":"block","value":0},{"title":"avoidance","value":0}],"talents":[343527,326732,115750,114154,152262,326734,343721],"items":[{"id":178933,"slot":"FINGER_1","ilvl":252,"enchantments":[6166],"sockets":[173128],"bonuses":[7622,7359,6652,1566,6646,7576],"spells":[]},{"id":186290,"slot":"FINGER_2","ilvl":252,"enchantments":[6166],"sockets":[173128],"bonuses":[7187,6652,1498,6646,7576],"spells":[]},{"id":179350,"slot":"TRINKET_1","ilvl":252,"enchantments":[],"sockets":[],"bonuses":[7608,7359,6652,1566,6646],"spells":[330323]},{"id":186423,"slot":"TRINKET_2","ilvl":252,"enchantments":[],"sockets":[],"bonuses":[7187,6652,1498,6646],"spells":[355313]},{"id":186403,"slot":"MAIN_HAND","ilvl":252,"enchantments":[6223],"sockets":[],"bonuses":[7187,6652,1498,6646],"spells":[]}],"legendaries":[{"id":171418,"slot":"LEGENDARY","ilvl":262,"enchantments":[],"sockets":[173128],"bonuses":[7679,7451,6649,6647,1559,6935],"spells":[355098]}],"covenant":{"covenant":"Kyrian","renownLevel":80,"soulbind":"Pelagos","traits":[{"tier":0,"id":328266,"type":"spell"},{"tier":1,"id":182778,"type":"item","socketType":"POTENCY"},{"tier":2,"id":328261,"type":"spell"},{"tier":3,"id":187506,"type":"item","socketType":"ENDURANCE"},{"tier":4,"id":328263,"type":"spell"},{"tier":5,"id":182608,"type":"item","socketType":"POTENCY"},{"tier":6,"id":182448,"type":"item","socketType":"FINESSE"},{"tier":7,"id":328257,"type":"spell"},{"tier":8,"id":182559,"type":"item","socketType":"POTENCY"},{"tier":9,"id":351146,"type":"spell"},{"tier":10,"id":182304,"type":"item","socketType":"ENDURANCE"},{"tier":11,"id":351149,"type":"spell"}]}},{"name":"Lecitania","realm":{"key":{"href":"https://eu.api.blizzard.com/data/wow/realm/589?namespace=dynamic-eu"},"name":"Kil'jaeden","id":589,"slug":"kiljaeden"},"mainStats":[{"title":"stamina","value":2690},{"title":"strength","value":1604},{"title":"intellect","value":452},{"title":"agility","value":158}],"offStats":[{"title":"haste","value":805},{"title":"mastery","value":668},{"title":"crit","value":385},{"title":"versatility","value":335}],"defStats":[{"title":"avoidance","value":39},{"title":"dodge","value":0},{"title":"parry","value":0},{"title":"block","value":0}],"talents":[269569,326732,234299,230332,152262,326734,343721],"items":[{"id":178848,"slot":"FINGER_1","ilvl":252,"enchantments":[6166],"sockets":[173130],"bonuses":[7622,7359,6652,1566,6646,7576],"spells":[]},{"id":178824,"slot":"FINGER_2","ilvl":252,"enchantments":[6166],"sockets":[173130],"bonuses":[7622,7359,6652,1566,6646,7576],"spells":[]},{"id":179342,"slot":"TRINKET_1","ilvl":246,"enchantments":[],"sockets":[],"bonuses":[7359,42,7606,1560,6646],"spells":[329831]},{"id":178771,"slot":"TRINKET_2","ilvl":252,"enchantments":[],"sockets":[],"bonuses":[7608,7359,6652,1566,6646],"spells":[345465]},{"id":179330,"slot":"MAIN_HAND","ilvl":252,"enchantments":[6229,6188],"sockets":[],"bonuses":[7650,7359,6652,1566,6646],"spells":[]}],"legendaries":[{"id":171416,"slot":"LEGENDARY","ilvl":262,"enchantments":[],"sockets":[],"bonuses":[7067,7451,6648,6649,1559],"spells":[337257]}],"covenant":{"covenant":"Kyrian","renownLevel":80,"soulbind":"Pelagos","traits":[{"tier":0,"id":328266,"type":"spell"},{"tier":1,"id":182778,"type":"item","socketType":"POTENCY"},{"tier":2,"id":328261,"type":"spell"},{"tier":3,"id":187506,"type":"item","socketType":"ENDURANCE"},{"tier":4,"id":328263,"type":"spell"},{"tier":5,"id":182608,"type":"item","socketType":"POTENCY"},{"tier":6,"id":182448,"type":"item","socketType":"FINESSE"},{"tier":7,"id":328257,"type":"spell"},{"tier":8,"id":182559,"type":"item","socketType":"POTENCY"},{"tier":9,"id":351146,"type":"spell"},{"tier":10,"id":182304,"type":"item","socketType":"ENDURANCE"},{"tier":11,"id":351149,"type":"spell"}]}},{"name":"Sephíroth","realm":{"key":{"href":"https://eu.api.blizzard.com/data/wow/realm/1382?namespace=dynamic-eu"},"name":"Sanguino","id":1382,"slug":"sanguino"},"mainStats":[{"title":"stamina","value":2698},{"title":"strength","value":1508},{"title":"intellect","value":452},{"title":"agility","value":158}],"offStats":[{"title":"haste","value":729},{"title":"mastery","value":614},{"title":"versatility","value":462},{"title":"crit","value":311}],"defStats":[{"title":"dodge","value":0},{"title":"parry","value":0},{"title":"block","value":0},{"title":"avoidance","value":0}],"talents":[343527,231832,234299,230332,152262,85804,343721],"items":[{"id":178736,"slot":"FINGER_1","ilvl":252,"enchantments":[6164],"sockets":[173129],"bonuses":[7622,7359,6652,1566,6646,7576],"spells":[]},{"id":178824,"slot":"FINGER_2","ilvl":252,"enchantments":[6164],"sockets":[173129],"bonuses":[7622,7359,6652,1566,6646,7576],"spells":[]},{"id":186423,"slot":"TRINKET_1","ilvl":252,"enchantments":[],"sockets":[],"bonuses":[7187,6652,1498,6646],"spells":[355313]},{"id":185197,"slot":"TRINKET_2","ilvl":239,"enchantments":[],"sockets":[],"bonuses":[7314,1511,6646],"spells":[345228]},{"id":186410,"slot":"MAIN_HAND","ilvl":259,"enchantments":[6229,6200],"sockets":[],"bonuses":[7187,6652,1498,6646,7748],"spells":[358571]}],"legendaries":[{"id":171418,"slot":"LEGENDARY","ilvl":262,"enchantments":[6192],"sockets":[173129],"bonuses":[7679,6649,6648,6935,7451,1559],"spells":[355098]}],"covenant":{"covenant":"Kyrian","renownLevel":80,"soulbind":"Pelagos","traits":[{"tier":0,"id":328266,"type":"spell"},{"tier":1,"id":182778,"type":"item","socketType":"POTENCY"},{"tier":2,"id":328261,"type":"spell"},{"tier":3,"id":182304,"type":"item","socketType":"ENDURANCE"},{"tier":4,"id":328265,"type":"spell"},{"tier":5,"id":182608,"type":"item","socketType":"POTENCY"},{"tier":6,"id":182448,"type":"item","socketType":"FINESSE"},{"tier":7,"id":328257,"type":"spell"},{"tier":8,"id":182559,"type":"item","socketType":"POTENCY"},{"tier":9,"id":351146,"type":"spell"},{"tier":10,"id":187506,"type":"item","socketType":"ENDURANCE"},{"tier":11,"id":351149,"type":"spell"}]}},{"name":"Тираэль","realm":{"key":{"href":"https://eu.api.blizzard.com/data/wow/realm/1924?namespace=dynamic-eu"},"name":"Booty Bay","id":1924,"slug":"booty-bay"},"mainStats":[{"title":"stamina","value":2664},{"title":"strength","value":1500},{"title":"intellect","value":450},{"title":"agility","value":157}],"offStats":[{"title":"mastery","value":881},{"title":"haste","value":771},{"title":"crit","value":501},{"title":"versatility","value":259}],"defStats":[{"title":"dodge","value":0},{"title":"parry","value":0},{"title":"block","value":0},{"title":"avoidance","value":0}],"talents":[343527,231832,115750,230332,152262,326734,343721],"items":[{"id":179355,"slot":"FINGER_1","ilvl":252,"enchantments":[6170],"sockets":[173129],"bonuses":[7622,7359,6652,1566,6646,7576],"spells":[]},{"id":186290,"slot":"FINGER_2","ilvl":252,"enchantments":[6166],"sockets":[],"bonuses":[7187,6652,7574,1498,6646],"spells":[]},{"id":185197,"slot":"TRINKET_1","ilvl":220,"enchantments":[],"sockets":[],"bonuses":[7311,1492,6646],"spells":[345228]},{"id":186423,"slot":"TRINKET_2","ilvl":252,"enchantments":[],"sockets":[],"bonuses":[7187,6652,1498,6646],"spells":[355313]},{"id":186403,"slot":"MAIN_HAND","ilvl":252,"enchantments":[6228],"sockets":[],"bonuses":[7187,6652,1498,6646],"spells":[]}],"legendaries":[{"id":171418,"slot":"LEGENDARY","ilvl":262,"enchantments":[],"sockets":[173128],"bonuses":[7679,7451,6650,6648,1559,6935],"spells":[355098]}],"covenant":{"covenant":"Kyrian","renownLevel":80,"soulbind":"Pelagos","traits":[{"tier":0,"id":328266,"type":"spell"},{"tier":1,"id":182778,"type":"item","socketType":"POTENCY"},{"tier":2,"id":328261,"type":"spell"},{"tier":3,"id":182307,"type":"item","socketType":"ENDURANCE"},{"tier":4,"id":328263,"type":"spell"},{"tier":5,"id":182559,"type":"item","socketType":"POTENCY"},{"tier":6,"id":182461,"type":"item","socketType":"FINESSE"},{"tier":7,"id":328257,"type":"spell"},{"tier":8,"id":182608,"type":"item","socketType":"POTENCY"},{"tier":9,"id":351146,"type":"spell"},{"tier":10,"id":187506,"type":"item","socketType":"ENDURANCE"},{"tier":11,"id":351149,"type":"spell"}]}},{"name":"Gilrael","realm":{"key":{"href":"https://eu.api.blizzard.com/data/wow/realm/1401?namespace=dynamic-eu"},"name":"Garrosh","id":1401,"slug":"garrosh"},"mainStats":[{"title":"stamina","value":2581},{"title":"strength","value":1455},{"title":"intellect","value":450},{"title":"agility","value":157}],"offStats":[{"title":"haste","value":878},{"title":"mastery","value":795},{"title":"crit","value":607},{"title":"versatility","value":0}],"defStats":[{"title":"dodge","value":0},{"title":"parry","value":0},{"title":"block","value":0},{"title":"avoidance","value":0}],"talents":[343527,326732,234299,114154,152262,326734,343721],"items":[{"id":179355,"slot":"FINGER_1","ilvl":252,"enchantments":[6168],"sockets":[173130],"bonuses":[7622,7359,6652,1566,6646,7576],"spells":[]},{"id":186290,"slot":"FINGER_2","ilvl":252,"enchantments":[6168],"sockets":[173130],"bonuses":[7187,6652,1498,6646,7576],"spells":[]},{"id":185818,"slot":"TRINKET_1","ilvl":233,"enchantments":[],"sockets":[],"bonuses":[7732,7359,6652,1550,6646],"spells":[351926]},{"id":185197,"slot":"TRINKET_2","ilvl":226,"enchantments":[],"sockets":[],"bonuses":[7312,1498,6646],"spells":[345228]},{"id":179330,"slot":"MAIN_HAND","ilvl":252,"enchantments":[6228,6200],"sockets":[],"bonuses":[7650,7359,6652,1566,6646],"spells":[]}],"legendaries":[{"id":171416,"slot":"LEGENDARY","ilvl":262,"enchantments":[],"sockets":[],"bonuses":[7067,6649,6648,7451,1559],"spells":[337257]}],"covenant":{"covenant":"Kyrian","renownLevel":80,"soulbind":"Pelagos","traits":[{"tier":0,"id":328266,"type":"spell"},{"tier":1,"id":182778,"type":"item","socketType":"POTENCY"},{"tier":2,"id":328261,"type":"spell"},{"tier":3,"id":182307,"type":"item","socketType":"ENDURANCE"},{"tier":4,"id":328263,"type":"spell"},{"tier":5,"id":182559,"type":"item","socketType":"POTENCY"},{"tier":6,"id":182461,"type":"item","socketType":"FINESSE"},{"tier":7,"id":328257,"type":"spell"},{"tier":8,"id":182608,"type":"item","socketType":"POTENCY"},{"tier":9,"id":351146,"type":"spell"},{"tier":10,"id":182304,"type":"item","socketType":"ENDURANCE"},{"tier":11,"id":351149,"type":"spell"}]}},{"name":"Chaosblack","realm":{"key":{"href":"https://eu.api.blizzard.com/data/wow/realm/1086?namespace=dynamic-eu"},"name":"La Croisade écarlate","id":1086,"slug":"la-croisade-écarlate"},"mainStats":[{"title":"stamina","value":2581},{"title":"strength","value":1512},{"title":"intellect","value":448},{"title":"agility","value":155}],"offStats":[{"title":"haste","value":789},{"title":"mastery","value":552},{"title":"crit","value":439},{"title":"versatility","value":257}],"defStats":[{"title":"avoidance","value":113},{"title":"dodge","value":0},{"title":"parry","value":0},{"title":"block","value":0}],"talents":[343527,231832,234299,114154,152262,326734,343721],"items":[{"id":179355,"slot":"FINGER_1","ilvl":246,"enchantments":[6168],"sockets":[],"bonuses":[7359,6652,7575,7620,1560,6646],"spells":[]},{"id":178736,"slot":"FINGER_2","ilvl":249,"enchantments":[6168],"sockets":[],"bonuses":[7621,7359,6652,7575,1563,6646],"spells":[]},{"id":178751,"slot":"TRINKET_1","ilvl":246,"enchantments":[],"sockets":[],"bonuses":[7359,6652,7606,1560,6646],"spells":[345548]},{"id":180118,"slot":"TRINKET_2","ilvl":246,"enchantments":[],"sockets":[],"bonuses":[7606,7359,40,1560,6646],"spells":[345533]},{"id":178780,"slot":"MAIN_HAND","ilvl":242,"enchantments":[6228],"sockets":[],"bonuses":[7359,6652,7647,1556,6646],"spells":[]}],"legendaries":[{"id":171412,"slot":"LEGENDARY","ilvl":262,"enchantments":[6214],"sockets":[],"bonuses":[7679,6648,6649,7451,1559],"spells":[355098]}],"covenant":{"covenant":"Kyrian","renownLevel":80,"soulbind":"Pelagos","traits":[{"tier":0,"id":328266,"type":"spell"},{"tier":1,"id":182559,"type":"item","socketType":"POTENCY"},{"tier":2,"id":328261,"type":"spell"},{"tier":3,"id":187506,"type":"item","socketType":"ENDURANCE"},{"tier":4,"id":328263,"type":"spell"},{"tier":5,"id":182778,"type":"item","socketType":"POTENCY"},{"tier":6,"id":182448,"type":"item","socketType":"FINESSE"},{"tier":7,"id":328257,"type":"spell"},{"tier":8,"id":182608,"type":"item","socketType":"POTENCY"},{"tier":9,"id":351146,"type":"spell"},{"tier":10,"id":182304,"type":"item","socketType":"ENDURANCE"},{"tier":11,"id":351149,"type":"spell"}]}},{"name":"Forthright","realm":{"key":{"href":"https://eu.api.blizzard.com/data/wow/realm/583?namespace=dynamic-eu"},"name":"Eredar","id":583,"slug":"eredar"},"mainStats":[{"title":"stamina","value":2632},{"title":"strength","value":1579},{"title":"intellect","value":452},{"title":"agility","value":158}],"offStats":[{"title":"versatility","value":707},{"title":"haste","value":672},{"title":"mastery","value":433},{"title":"crit","value":265}],"defStats":[{"title":"dodge","value":0},{"title":"parry","value":0},{"title":"block","value":0},{"title":"avoidance","value":0}],"talents":[267610,326732,115750,230332,152262,326734,317866],"items":[{"id":178736,"slot":"FINGER_1","ilvl":252,"enchantments":[6166],"sockets":[],"bonuses":[7622,7359,6652,7574,1566,6646],"spells":[]},{"id":178870,"slot":"FINGER_2","ilvl":252,"enchantments":[6168],"sockets":[],"bonuses":[7622,7359,6652,7575,1566,6646],"spells":[]},{"id":178771,"slot":"TRINKET_1","ilvl":246,"enchantments":[],"sockets":[],"bonuses":[7359,6652,7606,1560,6646],"spells":[345465]},{"id":179342,"slot":"TRINKET_2","ilvl":246,"enchantments":[],"sockets":[],"bonuses":[7359,6652,7606,1560,6646],"spells":[329831]},{"id":178866,"slot":"MAIN_HAND","ilvl":252,"enchantments":[6223],"sockets":[],"bonuses":[7650,7359,6652,1566,6646],"spells":[]}],"legendaries":[{"id":171418,"slot":"LEGENDARY","ilvl":262,"enchantments":[],"sockets":[173129],"bonuses":[7679,7451,6647,6650,1559,6935],"spells":[355098]}],"covenant":{"covenant":"Kyrian","renownLevel":80,"soulbind":"Forgelite Prime Mikanikos","traits":[{"tier":0,"id":333950,"type":"spell"},{"tier":1,"id":182778,"type":"item","socketType":"POTENCY"},{"tier":2,"id":331609,"type":"spell"},{"tier":3,"id":182448,"type":"item","socketType":"FINESSE"},{"tier":4,"id":331725,"type":"spell"},{"tier":5,"id":187506,"type":"item","socketType":"ENDURANCE"},{"tier":6,"id":182608,"type":"item","socketType":"POTENCY"},{"tier":7,"id":331611,"type":"spell"},{"tier":8,"id":182559,"type":"item","socketType":"POTENCY"},{"tier":9,"id":352186,"type":"spell"},{"tier":10,"id":182304,"type":"item","socketType":"ENDURANCE"},{"tier":11,"id":352188,"type":"spell"}]}},{"name":"Devcon","realm":{"key":{"href":"https://eu.api.blizzard.com/data/wow/realm/505?namespace=dynamic-eu"},"name":"Doomhammer","id":505,"slug":"doomhammer"},"mainStats":[{"title":"stamina","value":2554},{"title":"strength","value":1560},{"title":"intellect","value":450},{"title":"agility","value":157}],"offStats":[{"title":"haste","value":998},{"title":"mastery","value":500},{"title":"crit","value":350},{"title":"versatility","value":245}],"defStats":[{"title":"avoidance","value":50},{"title":"dodge","value":0},{"title":"parry","value":0},{"title":"block","value":0}],"talents":[269569,231832,234299,230332,152262,326734,343721],"items":[{"id":179355,"slot":"FINGER_1","ilvl":246,"enchantments":[6168],"sockets":[],"bonuses":[7359,6652,7575,7620,1560,6646],"spells":[]},{"id":178736,"slot":"FINGER_2","ilvl":233,"enchantments":[],"sockets":[],"bonuses":[7616,7359,6652,7575,1547,6646],"spells":[]},{"id":178811,"slot":"TRINKET_1","ilvl":249,"enchantments":[],"sockets":[],"bonuses":[7607,7359,1563,6646],"spells":[345739]},{"id":178771,"slot":"TRINKET_2","ilvl":246,"enchantments":[],"sockets":[],"bonuses":[7359,40,7606,1560,6646],"spells":[345465]},{"id":178866,"slot":"MAIN_HAND","ilvl":246,"enchantments":[6228],"sockets":[],"bonuses":[7648,7359,6652,1560,6646],"spells":[]}],"legendaries":[{"id":171418,"slot":"LEGENDARY","ilvl":262,"enchantments":[],"sockets":[173130],"bonuses":[7679,7451,6649,6648,1559,6935],"spells":[355098]}],"covenant":{"covenant":"Kyrian","renownLevel":80,"soulbind":"Pelagos","traits":[{"tier":0,"id":328266,"type":"spell"},{"tier":1,"id":182778,"type":"item","socketType":"POTENCY"},{"tier":2,"id":328261,"type":"spell"},{"tier":3,"id":187506,"type":"item","socketType":"ENDURANCE"},{"tier":4,"id":328263,"type":"spell"},{"tier":5,"id":182608,"type":"item","socketType":"POTENCY"},{"tier":6,"id":182448,"type":"item","socketType":"FINESSE"},{"tier":7,"id":328257,"type":"spell"},{"tier":8,"id":182559,"type":"item","socketType":"POTENCY"},{"tier":9,"id":351146,"type":"spell"},{"tier":10,"id":182304,"type":"item","socketType":"ENDURANCE"},{"tier":11,"id":351149,"type":"spell"}]}},{"name":"Vukan","realm":{"key":{"href":"https://eu.api.blizzard.com/data/wow/realm/1307?namespace=dynamic-eu"},"name":"Chamber of Aspects","id":1307,"slug":"chamber-of-aspects"},"mainStats":[{"title":"stamina","value":2526},{"title":"strength","value":1551},{"title":"intellect","value":450},{"title":"agility","value":157}],"offStats":[{"title":"versatility","value":783},{"title":"haste","value":548},{"title":"mastery","value":461},{"title":"crit","value":369}],"defStats":[{"title":"dodge","value":0},{"title":"parry","value":0},{"title":"block","value":0},{"title":"avoidance","value":0}],"talents":[269569,231832,234299,114154,223817,326734,343721],"items":[{"id":178736,"slot":"FINGER_1","ilvl":242,"enchantments":[6170],"sockets":[173129],"bonuses":[7359,6652,7619,1556,6646,7576],"spells":[]},{"id":178781,"slot":"FINGER_2","ilvl":246,"enchantments":[6170],"sockets":[173126],"bonuses":[7620,7359,6652,1560,6646,7576],"spells":[]},{"id":178861,"slot":"TRINKET_1","ilvl":242,"enchantments":[],"sockets":[],"bonuses":[7359,6652,7605,1556,6646],"spells":[342427]},{"id":179350,"slot":"TRINKET_2","ilvl":252,"enchantments":[],"sockets":[],"bonuses":[7608,7359,6652,1566,6646],"spells":[330323]},{"id":178780,"slot":"MAIN_HAND","ilvl":242,"enchantments":[6229],"sockets":[],"bonuses":[7359,6652,7647,1556,6646],"spells":[]}],"legendaries":[{"id":173242,"slot":"LEGENDARY","ilvl":262,"enchantments":[6202],"sockets":[],"bonuses":[7064,7451,6650,6648,1559],"spells":[337247]}],"covenant":{"covenant":"Kyrian","renownLevel":80,"soulbind":"Pelagos","traits":[{"tier":0,"id":328266,"type":"spell"},{"tier":1,"id":182778,"type":"item","socketType":"POTENCY"},{"tier":2,"id":328261,"type":"spell"},{"tier":3,"id":187506,"type":"item","socketType":"ENDURANCE"},{"tier":4,"id":328263,"type":"spell"},{"tier":5,"id":182608,"type":"item","socketType":"POTENCY"},{"tier":6,"id":182448,"type":"item","socketType":"FINESSE"},{"tier":7,"id":328257,"type":"spell"},{"tier":8,"id":182559,"type":"item","socketType":"POTENCY"},{"tier":9,"id":351146,"type":"spell"},{"tier":10,"id":182307,"type":"item","socketType":"ENDURANCE"},{"tier":11,"id":351149,"type":"spell"}]}},{"name":"Matrlx","realm":{"key":{"href":"https://eu.api.blizzard.com/data/wow/realm/1305?namespace=dynamic-eu"},"name":"Kazzak","id":1305,"slug":"kazzak"},"mainStats":[{"title":"stamina","value":2702},{"title":"strength","value":1580},{"title":"intellect","value":452},{"title":"agility","value":158}],"offStats":[{"title":"mastery","value":673},{"title":"haste","value":606},{"title":"versatility","value":469},{"title":"crit","value":324}],"defStats":[{"title":"avoidance","value":52},{"title":"dodge","value":0},{"title":"parry","value":0},{"title":"block","value":0}],"talents":[343527,326732,115750,230332,152262,326734,343721],"items":[{"id":178933,"slot":"FINGER_1","ilvl":252,"enchantments":[6166],"sockets":[173130],"bonuses":[7622,7359,6652,1566,6646,7576],"spells":[]},{"id":178870,"slot":"FINGER_2","ilvl":252,"enchantments":[6166],"sockets":[173130],"bonuses":[7622,7359,6652,1566,6646,7576],"spells":[]},{"id":179342,"slot":"TRINKET_1","ilvl":252,"enchantments":[],"sockets":[],"bonuses":[7608,7359,6652,1566,6646],"spells":[329831]},{"id":186438,"slot":"TRINKET_2","ilvl":246,"enchantments":[],"sockets":[],"bonuses":[7188,6652,1485,6646],"spells":[355297,355298]},{"id":186410,"slot":"MAIN_HAND","ilvl":246,"enchantments":[6228,6200],"sockets":[],"bonuses":[7188,41,1485,6646,7742,7743,7744],"spells":[357585,358567]}],"legendaries":[{"id":171418,"slot":"LEGENDARY","ilvl":262,"enchantments":[4223],"sockets":[173130],"bonuses":[7679,6649,6648,6935,7451,1559],"spells":[355098]}],"covenant":{"covenant":"Kyrian","renownLevel":80,"soulbind":"Forgelite Prime Mikanikos","traits":[{"tier":0,"id":333950,"type":"spell"},{"tier":1,"id":182778,"type":"item","socketType":"POTENCY"},{"tier":2,"id":331609,"type":"spell"},{"tier":3,"id":182448,"type":"item","socketType":"FINESSE"},{"tier":4,"id":331726,"type":"spell"},{"tier":5,"id":182307,"type":"item","socketType":"ENDURANCE"},{"tier":6,"id":182304,"type":"item","socketType":"ENDURANCE"},{"tier":7,"id":333935,"type":"spell"},{"tier":8,"id":182462,"type":"item","socketType":"POTENCY"},{"tier":9,"id":352186,"type":"spell"},{"tier":10,"id":182336,"type":"item","socketType":"ENDURANCE"},{"tier":11,"id":352188,"type":"spell"}]}}]}